{"trial_id": "47", "hyperparameters": {"space": [{"class_name": "Int", "config": {"name": "n_neurons1", "default": null, "conditions": [], "min_value": 275, "max_value": 300, "step": 1, "sampling": "linear"}}, {"class_name": "Int", "config": {"name": "n_neurons2", "default": null, "conditions": [], "min_value": 75, "max_value": 125, "step": 1, "sampling": "linear"}}, {"class_name": "Float", "config": {"name": "learning_rate", "default": 0.3, "conditions": [], "min_value": 0.3, "max_value": 0.6, "step": null, "sampling": "log"}}, {"class_name": "Choice", "config": {"name": "optimizer", "default": "sgd", "conditions": [], "values": ["sgd", "adam"], "ordered": false}}], "values": {"n_neurons1": 293, "n_neurons2": 118, "learning_rate": 0.3645159123435937, "optimizer": "adam"}}, "metrics": {"metrics": {"loss": {"direction": "min", "observations": [{"value": [2.3345377445220947], "step": 5}]}, "accuracy": {"direction": "max", "observations": [{"value": [0.10239999741315842], "step": 5}]}, "val_loss": {"direction": "min", "observations": [{"value": [2.3659257888793945], "step": 5}]}, "val_accuracy": {"direction": "max", "observations": [{"value": [0.11699999868869781], "step": 5}]}}}, "score": 0.11699999868869781, "best_step": 5, "status": "COMPLETED", "message": null}